pyfieldimager/__init__.py
pyfieldimager/__version__.py
pyfieldimager/export.py
pyfieldimager/index.py
pyfieldimager/main.py
pyfieldimager-0.9.3.2.dist-info/licenses/LICENSE
pyfieldimager-0.9.3.2.dist-info/METADATA
pyfieldimager-0.9.3.2.dist-info/WHEEL
pyfieldimager-0.9.3.2.dist-info/entry_points.txt
pyfieldimager-0.9.3.2.dist-info/top_level.txt
pyfieldimager-0.9.3.2.dist-info/RECORD
