Metadata-Version: 2.4
Name: pyfieldimager
Version: 0.9.3.2
Summary: A Python package for field image analysis.
Home-page: https://github.com/nudoi/pyfieldimager
Author: doi
Author-email: doi <doi@doilab.open.ad.jp>
License:                   GNU LESSER GENERAL PUBLIC LICENSE
Project-URL: Homepage, https://github.com/nudoi/pyfieldimager
Project-URL: Repository, https://github.com/nudoi/pyfieldimager.git
Project-URL: Issues, https://github.com/nudoi/pyfieldimager/issues
Keywords: field,image,python
Classifier: Development Status :: 3 - Alpha
Classifier: Intended Audience :: Developers
Classifier: License :: OSI Approved :: GNU Lesser General Public License v2 (LGPLv2)
Classifier: Programming Language :: Python :: 3
Classifier: Programming Language :: Python :: 3.9
Classifier: Programming Language :: Python :: 3.10
Classifier: Operating System :: OS Independent
Classifier: Topic :: Scientific/Engineering
Classifier: Topic :: Software Development
Classifier: Typing :: Typed
License-File: LICENSE
Dynamic: author
Dynamic: home-page
Dynamic: license-file
